triangles/__init__.py
triangles/triangles.py
triangles-1.0.0.dist-info/LICENSE
triangles-1.0.0.dist-info/METADATA
triangles-1.0.0.dist-info/WHEEL
triangles-1.0.0.dist-info/top_level.txt
triangles-1.0.0.dist-info/RECORD
