Metadata-Version: 2.1
Name: triangles
Version: 1.0.0
Summary: A solver for triangle sides and angles
Home-page: https://github.com/placeholder
Author: Hemendu Roy
Author-email: hemenduroy@yahoo.com
License: MIT License
Platform: UNKNOWN
Classifier: License :: OSI Approved :: MIT License
Classifier: Programming Language :: Python :: 3
Classifier: Operating System :: OS Independent
Requires-Python: >=3.6
License-File: LICENSE
